.gitignore
HISTORY.rst
LICENSE
README.rst
setup.py
cmsplugin_phlog/__init__.py
cmsplugin_phlog/admin.py
cmsplugin_phlog/cms_plugins.py
cmsplugin_phlog/models.py
cmsplugin_phlog.egg-info/PKG-INFO
cmsplugin_phlog.egg-info/SOURCES.txt
cmsplugin_phlog.egg-info/dependency_links.txt
cmsplugin_phlog.egg-info/not-zip-safe
cmsplugin_phlog.egg-info/requires.txt
cmsplugin_phlog.egg-info/top_level.txt
cmsplugin_phlog/forms/__init__.py
cmsplugin_phlog/forms/fields.py
cmsplugin_phlog/forms/forms.py
cmsplugin_phlog/forms/widgets.py
cmsplugin_phlog/migrations/0001_initial.py
cmsplugin_phlog/migrations/0002_v0_2.py
cmsplugin_phlog/migrations/0003_v0_2_3.py
cmsplugin_phlog/migrations/__init__.py
cmsplugin_phlog/static/phlog/css/plugins_widget.css
cmsplugin_phlog/static/phlog/images/pluginlist-delete.png
cmsplugin_phlog/static/phlog/images/sitemap-li-bg.jpg
cmsplugin_phlog/static/phlog/images/sitemap-li-drag.gif
cmsplugin_phlog/static/phlog/js/init.js
cmsplugin_phlog/static/phlog/js/plugins_widget.js
cmsplugin_phlog/templates/admin/phlog/widgets/installed_plugins_inc.html
cmsplugin_phlog/templates/admin/phlog/widgets/plugin_item.html
cmsplugin_phlog/templates/admin/phlog/widgets/plugins.html
cmsplugin_phlog/templates/admin/photologue/orderedgallery/change_form.html
cmsplugin_phlog/templates/admin/photologue/orderedgallery/inline_photos.html
cmsplugin_phlog/templates/cms/plugins/phlog/gallery.html
cmsplugin_phlog/templates/cms/plugins/phlog/gallery_change_form.html
cmsplugin_phlog/templates/cms/plugins/phlog/main column-gallery.html
cmsplugin_phlog/templates/cms/plugins/phlog/main content-gallery.html
cmsplugin_phlog/templates/cms/plugins/phlog/photo.html