Metadata-Version: 1.1
Name: cmsplugin-phlog
Version: 0.3.1
Summary: Django CMS Plugin for Photologue galleries
Home-page: https://github.com/benliles/cmsplugin-phlog
Author: Benjamin Liles
Author-email: ben@ltwebdev.com
License: UNKNOWN
Keywords: django cms plugin photologue
Platform: UNKNOWN
Classifier: Framework :: Django
Classifier: Development Status :: 3 - Alpha
Classifier: Programming Language :: Python
Classifier: Topic :: Multimedia :: Graphics
Classifier: Topic :: Software Development :: Libraries :: Python Modules
Classifier: License :: OSI Approved :: Apache Software License
